DataElevate/EDAerror.py
DataElevate/GoogleDrive_api.py
DataElevate/__init__.py
DataElevate/download.py
DataElevate/env.py
DataElevate/extractor.py
DataElevate/kaggle_api.py
DataElevate/load_data.py
DataElevate/load_data_api.py
DataElevate-1.0.7.dist-info/LICENSE
DataElevate-1.0.7.dist-info/METADATA
DataElevate-1.0.7.dist-info/WHEEL
DataElevate-1.0.7.dist-info/top_level.txt
DataElevate-1.0.7.dist-info/RECORD
