Metadata-Version: 2.1
Name: DataElevate
Version: 1.0.7
Summary: DataElevate is a Python library designed to simplify and enhance data management and analysis workflows. It offers tools for seamless data access, transformation, and integration with external services like Google Drive, ensuring security and ease of use.
Home-page: https://github.com/Monal-Bhiwgade/DataElevate
Author: Monal Bhiwgade
Author-email: 3051monal@gmail.com
Keywords: DataElevate,Data,Data Management,Data Analysis,Data Transformation,Data Integration,Drive,Drive File,Folder,Downlaod,Elevate,Kaggle,Dataset Download,Dataset
Classifier: Programming Language :: Python :: 3
Classifier: License :: OSI Approved :: MIT License
Classifier: Operating System :: OS Independent
Requires-Python: >=3.8
License-File: LICENSE
Requires-Dist: google-auth
Requires-Dist: google-auth-oauthlib
Requires-Dist: google-api-python-client
Requires-Dist: requests
Requires-Dist: pandas
Requires-Dist: seaborn
Requires-Dist: numpy
Requires-Dist: matplotlib
Requires-Dist: kagglehub
Requires-Dist: gdown
Requires-Dist: mysql
Requires-Dist: google-auth-httplib2
Requires-Dist: openpyxl
Requires-Dist: SQLAlchemy
Requires-Dist: psycopg2
Requires-Dist: python-dotenv
Requires-Dist: tqdm
